LICENSE
README.md
setup.py
omeClust/__init__.py
omeClust/cluster_generator.py
omeClust/config.py
omeClust/dataprocess.py
omeClust/distance.py
omeClust/omeClust.py
omeClust/utilities.py
omeClust/viz.py
omeClust.egg-info/PKG-INFO
omeClust.egg-info/SOURCES.txt
omeClust.egg-info/dependency_links.txt
omeClust.egg-info/entry_points.txt
omeClust.egg-info/not-zip-safe
omeClust.egg-info/requires.txt
omeClust.egg-info/top_level.txt
omeClust/tests/__init__.py
omeClust/tests/advanced_tests_distance.py
omeClust/tests/basic_tests_stats.py
omeClust/tests/m2clust_test.py