Metadata-Version: 2.1
Name: omeClust
Version: 1.1.9
Summary: omeClust: multi-resolution clustering
Home-page: http://github.com/omicsEye/omeClust
Author: Ali Rahnavard
Author-email: gholamali.rahnavard@gmail.com
License: MIT
Keywords: clustering,multi-resolution,hierarchically
Platform: Linux
Platform: MacOS
Platform: Windows
Classifier: Programming Language :: Python
Classifier: Development Status :: 5 - Production/Stable
Classifier: Environment :: Console
Classifier: Operating System :: MacOS
Classifier: Operating System :: Unix
Classifier: Operating System :: Microsoft :: Windows
Classifier: Programming Language :: Python :: 2.7
Classifier: Topic :: Scientific/Engineering :: Bio-Informatics
License-File: LICENSE
